{
  "version": 73,
  "total_agents": 25,
  "completed_agents": [
    "baseball-match-data-agent",
    "baseball-stats-aggregation-agent",
    "baseball-historical-data-agent",
    "baseball-prediction-model-agent",
    "baseball-visualization-agent",
    "game-analytics-agent",
    "game-metrics-collector-agent",
    "game-behavior-tracker-agent",
    "game-engagement-agent",
    "game-performance-metrics-agent",
    "erotic-recommendation-engine-agent",
    "erotic-trend-analyzer-agent",
    "erotic-popularity-agent",
    "erotic-personalization-agent",
    "erotic-discovery-agent",
    "data-pipeline-agent",
    "etl-agent",
    "data-warehouse-agent",
    "data-lake-agent",
    "data-stream-agent",
    "security-monitoring-agent",
    "security-alerting-agent",
    "siem-agent",
    "soar-agent",
    "incident-response-agent"
  ],
  "started_at": "2026-02-14T06:19:01.582211",
  "completed_at": "2026-02-14T06:19:01.595393",
  "status": "completed"
}